tokker/__init__.py
tokker/__main__.py
tokker/api.py
tokker/error_handler.py
tokker/messages.py
tokker/runtime.py
tokker/utils.py
tokker/cli/__init__.py
tokker/cli/arguments.py
tokker/cli/config.py
tokker/cli/history.py
tokker/cli/tokenize.py
tokker/cli/commands/clear_history.py
tokker/cli/commands/list_models.py
tokker/cli/commands/set_default_model.py
tokker/cli/commands/set_default_output.py
tokker/cli/commands/show_history.py
tokker/cli/commands/tokenize_text.py
tokker/cli/output/base_json.py
tokker/cli/output/formats.py
tokker/cli/output/utils_output.py
tokker/models/__init__.py
tokker/models/discovery.py
tokker/models/model_index.py
tokker/models/registry.py
tokker/providers/__init__.py
tokker/providers/google.py
tokker/providers/huggingface.py
tokker/providers/imports.py
tokker/providers/instances.py
tokker/providers/provider.py
tokker/providers/tiktoken.py
tokker-0.3.9.dist-info/licenses/LICENSE
tokker-0.3.9.dist-info/METADATA
tokker-0.3.9.dist-info/WHEEL
tokker-0.3.9.dist-info/entry_points.txt
tokker-0.3.9.dist-info/top_level.txt
tokker-0.3.9.dist-info/RECORD
