Metadata-Version: 2.4
Name: tokker
Version: 0.3.9
Summary: Tokker: a fast local-first CLI tokenizer with all the best models in one place
Author-email: igoakulov <igoruphere@gmail.com>
License-Expression: MIT
Project-URL: Homepage, https://github.com/igoakulov/tokker
Project-URL: Repository, https://github.com/igoakulov/tokker
Project-URL: Issues, https://github.com/igoakulov/tokker/issues
Project-URL: Documentation, https://github.com/igoakulov/tokker#readme
Keywords: cli,gemini,google,gpt,hf,huggingface,models,openai,tiktoken,tokenization,tokens,transformers
Classifier: Development Status :: 4 - Beta
Classifier: Intended Audience :: Developers
Classifier: Programming Language :: Python :: 3
Classifier: Programming Language :: Python :: 3.11
Classifier: Programming Language :: Python :: 3.12
Classifier: Topic :: Text Processing :: Linguistic
Classifier: Topic :: Software Development :: Libraries :: Python Modules
Classifier: Environment :: Console
Requires-Python: >=3.11
License-File: LICENSE
Provides-Extra: transformers
Requires-Dist: transformers>=4.40.0; extra == "transformers"
Provides-Extra: tiktoken
Requires-Dist: tiktoken>=0.5.0; extra == "tiktoken"
Provides-Extra: google-genai
Requires-Dist: google-genai>=0.3.0; extra == "google-genai"
Provides-Extra: all
Requires-Dist: transformers>=4.40.0; extra == "all"
Requires-Dist: tiktoken>=0.5.0; extra == "all"
Requires-Dist: google-genai>=0.3.0; extra == "all"
Dynamic: license-file
